blacken_docs_jb.py
blacken_docs_jb-0.6.2.dist-info/LICENSE
blacken_docs_jb-0.6.2.dist-info/METADATA
blacken_docs_jb-0.6.2.dist-info/WHEEL
blacken_docs_jb-0.6.2.dist-info/entry_points.txt
blacken_docs_jb-0.6.2.dist-info/top_level.txt
blacken_docs_jb-0.6.2.dist-info/RECORD
