Metadata-Version: 2.1
Name: blacken-docs-jb
Version: 0.6.2
Summary: Run `black` on python code blocks in documentation files (also for jupyterbook)
Home-page: https://github.com/finsberg/blacken-docs-jb
Author: Henrik Finsberg
Author-email: henriknf@simula.no
License: MIT
Classifier: License :: OSI Approved :: MIT License
Classifier: Programming Language :: Python :: 3
Classifier: Programming Language :: Python :: 3 :: Only
Classifier: Programming Language :: Python :: Implementation :: CPython
Classifier: Programming Language :: Python :: Implementation :: PyPy
Requires-Python: >=3.7
License-File: LICENSE
Requires-Dist: blacken-docs
Requires-Dist: ipython
Requires-Dist: tokenize-rt
